pqcrypto/.gitkeep
pqcrypto/__init__.py
pqcrypto/_kem/hqc_128.cpython-310-aarch64-linux-gnu.so
pqcrypto/_kem/hqc_128.cpython-311-aarch64-linux-musl.so
pqcrypto/_kem/hqc_128.cpython-39-aarch64-linux-gnu.so
pqcrypto/_kem/hqc_192.cpython-310-aarch64-linux-gnu.so
pqcrypto/_kem/hqc_192.cpython-311-aarch64-linux-musl.so
pqcrypto/_kem/hqc_192.cpython-39-aarch64-linux-gnu.so
pqcrypto/_kem/hqc_256.cpython-310-aarch64-linux-gnu.so
pqcrypto/_kem/hqc_256.cpython-311-aarch64-linux-musl.so
pqcrypto/_kem/hqc_256.cpython-39-aarch64-linux-gnu.so
pqcrypto/_kem/mceliece348864.cpython-310-aarch64-linux-gnu.so
pqcrypto/_kem/mceliece348864.cpython-311-aarch64-linux-musl.so
pqcrypto/_kem/mceliece348864.cpython-39-aarch64-linux-gnu.so
pqcrypto/_kem/mceliece348864f.cpython-310-aarch64-linux-gnu.so
pqcrypto/_kem/mceliece348864f.cpython-311-aarch64-linux-musl.so
pqcrypto/_kem/mceliece348864f.cpython-39-aarch64-linux-gnu.so
pqcrypto/_kem/mceliece460896.cpython-310-aarch64-linux-gnu.so
pqcrypto/_kem/mceliece460896.cpython-311-aarch64-linux-musl.so
pqcrypto/_kem/mceliece460896.cpython-39-aarch64-linux-gnu.so
pqcrypto/_kem/mceliece460896f.cpython-310-aarch64-linux-gnu.so
pqcrypto/_kem/mceliece460896f.cpython-311-aarch64-linux-musl.so
pqcrypto/_kem/mceliece460896f.cpython-39-aarch64-linux-gnu.so
pqcrypto/_kem/mceliece6688128.cpython-310-aarch64-linux-gnu.so
pqcrypto/_kem/mceliece6688128.cpython-311-aarch64-linux-musl.so
pqcrypto/_kem/mceliece6688128.cpython-39-aarch64-linux-gnu.so
pqcrypto/_kem/mceliece6688128f.cpython-310-aarch64-linux-gnu.so
pqcrypto/_kem/mceliece6688128f.cpython-311-aarch64-linux-musl.so
pqcrypto/_kem/mceliece6688128f.cpython-39-aarch64-linux-gnu.so
pqcrypto/_kem/mceliece6960119.cpython-310-aarch64-linux-gnu.so
pqcrypto/_kem/mceliece6960119.cpython-311-aarch64-linux-musl.so
pqcrypto/_kem/mceliece6960119.cpython-39-aarch64-linux-gnu.so
pqcrypto/_kem/mceliece6960119f.cpython-310-aarch64-linux-gnu.so
pqcrypto-0.3.3.dist-info/METADATA
pqcrypto-0.3.3.dist-info/WHEEL
pqcrypto-0.3.3.dist-info/RECORD
pqcrypto-0.3.3.dist-info/licenses/LICENSE
pqcrypto-0.3.3.dist-info/licenses/NOTICE
