Metadata-Version: 2.4
Name: pqcrypto
Version: 0.3.3
Summary: Post-quantum cryptography for Python.
Project-URL: Repository, https://github.com/backbone-hq/pqcrypto
Project-URL: Bug Tracker, https://github.com/backbone-hq/pqcrypto/issues
Author-email: Backbone Authors <root@backbone.dev>
License-Expression: Apache-2.0
License-File: LICENSE
License-File: NOTICE
Keywords: cryptography,post-quantum,pqclean,security
Classifier: Development Status :: 4 - Beta
Classifier: Intended Audience :: Developers
Classifier: Intended Audience :: Science/Research
Classifier: Intended Audience :: System Administrators
Classifier: Intended Audience :: Telecommunications Industry
Classifier: Programming Language :: C
Classifier: Programming Language :: Python :: 3
Classifier: Topic :: Security
Classifier: Topic :: Security :: Cryptography
Classifier: Topic :: Software Development
Classifier: Topic :: Software Development :: Libraries
Classifier: Topic :: Utilities
Requires-Python: >=3.9
